PcbDrawToPdf/PcbDrawToPdf.py
PcbDrawToPdf/__init__.py
PcbDrawToPdf/ui.py
pcbdrawtopdf-1.0.2.dist-info/entry_points.txt
pcbdrawtopdf-1.0.2.dist-info/WHEEL
pcbdrawtopdf-1.0.2.dist-info/METADATA
pcbdrawtopdf-1.0.2.dist-info/RECORD
