Metadata-Version: 2.3
Name: PcbDrawToPdf
Version: 1.0.2
Summary: PcbDrawToPDF exports the masks employed by PcbDraw in order to apply masking on Adobe software and be able to save on PDF correctly.
Author-email: Rafael de la Rosa <rafodelarosa.og@gmail.com>
Requires-Python: >=3.10
Classifier: Programming Language :: Python :: 3
Classifier: License :: OSI Approved :: MIT License
Classifier: Operating System :: OS Independent
Requires-Dist: click
Requires-Dist: lxml
Project-URL: Homepage, https://github.com/rafo-og/PcbDrawToPdf
